README.rst
setup.py
/home/can/Projects/score/py.uws/lib/uWebSockets/src/Epoll.cpp
/home/can/Projects/score/py.uws/lib/uWebSockets/src/Extensions.cpp
/home/can/Projects/score/py.uws/lib/uWebSockets/src/Group.cpp
/home/can/Projects/score/py.uws/lib/uWebSockets/src/HTTPSocket.cpp
/home/can/Projects/score/py.uws/lib/uWebSockets/src/Hub.cpp
/home/can/Projects/score/py.uws/lib/uWebSockets/src/Networking.cpp
/home/can/Projects/score/py.uws/lib/uWebSockets/src/Node.cpp
/home/can/Projects/score/py.uws/lib/uWebSockets/src/Socket.cpp
/home/can/Projects/score/py.uws/lib/uWebSockets/src/WebSocket.cpp
score/__init__.py
score.uws.egg-info/PKG-INFO
score.uws.egg-info/SOURCES.txt
score.uws.egg-info/dependency_links.txt
score.uws.egg-info/namespace_packages.txt
score.uws.egg-info/not-zip-safe
score.uws.egg-info/requires.txt
score.uws.egg-info/top_level.txt
score/uws/__init__.py
score/uws/_init.py
score/uws/worker.py
score/uws/_hub/__init__.py
score/uws/_hub/hub.cpp